docximg2md/__init__.py
docximg2md/program.py
docximg2md-0.9.0.dist-info/METADATA
docximg2md-0.9.0.dist-info/WHEEL
docximg2md-0.9.0.dist-info/entry_points.txt
docximg2md-0.9.0.dist-info/top_level.txt
docximg2md-0.9.0.dist-info/RECORD
