Metadata-Version: 2.1
Name: docximg2md
Version: 0.9.0
Summary: Python command line program for taking the images in a word document to markdown
Home-page: UNKNOWN
Author: Isabel Sandstrøm
Author-email: isabel@hermit.no
License: UNKNOWN
Platform: UNKNOWN
Classifier: Programming Language :: Python :: 3
Classifier: License :: OSI Approved :: MIT License
Classifier: Operating System :: OS Independent
Requires-Python: >=3.6
Requires-Dist: PyPDF2 (>=1.26.0)
